bytesrepr/.__init__.py.un~
bytesrepr/__init__.py
bytesrepr-0.0.2.dist-info/WHEEL
bytesrepr-0.0.2.dist-info/METADATA
bytesrepr-0.0.2.dist-info/RECORD
