Metadata-Version: 1.2
Name: bytesrepr
Version: 0.0.2
Summary: A simple IPython extension which changes the representation of bytes to
Home-page: https://github.com/Carreau/bytesrepr
License: UNKNOWN
Author: Matthias Bussonnier
Author-email: bussonniermatthias@gmail.com
Requires-Python: >=3.3
Classifier: License :: OSI Approved :: BSD License
